nyeok_database_core/__init__.py
nyeok_database_core/db.py
nyeok_database_core/py.typed
nyeok_database_core/tables.py
nyeok_database_core/with_enforcer.py
nyeok_database_core-0.1.0.dist-info/METADATA
nyeok_database_core-0.1.0.dist-info/WHEEL
nyeok_database_core-0.1.0.dist-info/RECORD
